{
    "2025-02-15 00:00:00": [
        {
            "user": "U082TL6CJA1",
            "type": "message",
            "ts": "1739642813.032909",
            "edited": {
                "user": "U082TL6CJA1",
                "ts": "1739642870.000000"
            },
            "client_msg_id": "88c2d5f8-32e9-4114-8e4d-cd37df8f3fe2",
            "text": "15 Feb 2025\nDone\n\u2022 Raised issues (<https://github.com/ohcnetwork/care_fe/issues/10621|issue1> , <https://github.com/ohcnetwork/care_fe/issues/10621|issue2> )\n\u2022 Went through FE codebase\nNext\n\u2022 Waiting to get issues assigned ",
            "team": "TC99SV7B6",
            "blocks": [
                {
                    "type": "rich_text",
                    "block_id": "Yjht+",
                    "elements": [
                        {
                            "type": "rich_text_section",
                            "elements": [
                                {
                                    "type": "text",
                                    "text": "15 Feb 2025\nDone\n"
                                }
                            ]
                        },
                        {
                            "type": "rich_text_list",
                            "elements": [
                                {
                                    "type": "rich_text_section",
                                    "elements": [
                                        {
                                            "type": "text",
                                            "text": "Raised issues ("
                                        },
                                        {
                                            "type": "link",
                                            "url": "https://github.com/ohcnetwork/care_fe/issues/10621",
                                            "text": "issue1"
                                        },
                                        {
                                            "type": "text",
                                            "text": " , "
                                        },
                                        {
                                            "type": "link",
                                            "url": "https://github.com/ohcnetwork/care_fe/issues/10621",
                                            "text": "issue2"
                                        },
                                        {
                                            "type": "text",
                                            "text": " )"
                                        }
                                    ]
                                },
                                {
                                    "type": "rich_text_section",
                                    "elements": [
                                        {
                                            "type": "text",
                                            "text": "Went through FE codebase"
                                        }
                                    ]
                                }
                            ],
                            "style": "bullet",
                            "indent": 0,
                            "border": 0
                        },
                        {
                            "type": "rich_text_section",
                            "elements": [
                                {
                                    "type": "text",
                                    "text": "Next\n"
                                }
                            ]
                        },
                        {
                            "type": "rich_text_list",
                            "elements": [
                                {
                                    "type": "rich_text_section",
                                    "elements": [
                                        {
                                            "type": "text",
                                            "text": "Waiting to get issues assigned "
                                        }
                                    ]
                                }
                            ],
                            "style": "bullet",
                            "indent": 0,
                            "border": 0
                        }
                    ]
                }
            ],
            "reactions": [
                {
                    "name": "rocket",
                    "users": [
                        "U0576PEACG0"
                    ],
                    "count": 1
                }
            ]
        }
    ],
    "2025-02-17 00:00:00": [
        {
            "user": "U082TL6CJA1",
            "type": "message",
            "ts": "1739810007.316409",
            "client_msg_id": "a6c2126a-c775-4a10-a271-ae0214fa678b",
            "text": "Feb 17\nDone :\nRaised a new issue and waiting for feedback from <@U07NXCASM89>\nLearnt about Cypress tests and Raviger Routers\nNext:\nLooking for new issues",
            "team": "TC99SV7B6",
            "blocks": [
                {
                    "type": "rich_text",
                    "block_id": "etyZq",
                    "elements": [
                        {
                            "type": "rich_text_section",
                            "elements": [
                                {
                                    "type": "text",
                                    "text": "Feb 17\nDone :\nRaised a new issue and waiting for feedback from "
                                },
                                {
                                    "type": "user",
                                    "user_id": "U07NXCASM89"
                                },
                                {
                                    "type": "text",
                                    "text": "\nLearnt about Cypress tests and Raviger Routers\nNext:\nLooking for new issues"
                                }
                            ]
                        }
                    ]
                }
            ]
        }
    ],
    "2025-02-20 00:00:00": [
        {
            "user": "U082TL6CJA1",
            "type": "message",
            "ts": "1740072729.857959",
            "client_msg_id": "f8f03f79-5c28-492d-864b-79fe496b1b4f",
            "text": "Feb 19 , 20\nDone\n\u2022 Worked on Assigned issue\n\u2022 Raised new issues\nNext\n\u2022 Raise PR for the issue\n\u2022 Looking for new issues\n",
            "team": "TC99SV7B6",
            "blocks": [
                {
                    "type": "rich_text",
                    "block_id": "p7+2V",
                    "elements": [
                        {
                            "type": "rich_text_section",
                            "elements": [
                                {
                                    "type": "text",
                                    "text": "Feb 19 , 20\nDone\n"
                                }
                            ]
                        },
                        {
                            "type": "rich_text_list",
                            "elements": [
                                {
                                    "type": "rich_text_section",
                                    "elements": [
                                        {
                                            "type": "text",
                                            "text": "Worked on Assigned issue"
                                        }
                                    ]
                                },
                                {
                                    "type": "rich_text_section",
                                    "elements": [
                                        {
                                            "type": "text",
                                            "text": "Raised new issues"
                                        }
                                    ]
                                }
                            ],
                            "style": "bullet",
                            "indent": 0,
                            "border": 0
                        },
                        {
                            "type": "rich_text_section",
                            "elements": [
                                {
                                    "type": "text",
                                    "text": "Next\n"
                                }
                            ]
                        },
                        {
                            "type": "rich_text_list",
                            "elements": [
                                {
                                    "type": "rich_text_section",
                                    "elements": [
                                        {
                                            "type": "text",
                                            "text": "Raise PR for the issue"
                                        }
                                    ]
                                },
                                {
                                    "type": "rich_text_section",
                                    "elements": [
                                        {
                                            "type": "text",
                                            "text": "Looking for new issues"
                                        }
                                    ]
                                }
                            ],
                            "style": "bullet",
                            "indent": 0,
                            "border": 0
                        },
                        {
                            "type": "rich_text_section",
                            "elements": []
                        }
                    ]
                }
            ]
        }
    ]
}