{
  "last_updated": "2023-11-21T06:46:36.000Z",
  "activity": [
    {
      "type": "pr_collaborated",
      "title": "coronasafe/care_fe#6600",
      "time": "2023-11-21T06:46:36.000Z",
      "link": "https://github.com/coronasafe/care_fe/pull/6600",
      "text": "Production Release Mid November",
      "collaborated_with": [
        "sainak",
        "nihal467",
        "rithviknishad",
        "shyamprakash123",
        "AshrafMd-1",
        "thedevildude",
        "Ashesh3",
        "Omkar76",
        "sriharsh05",
        "Pranshu1902",
        "kshitijv256",
        "konavivekramakrishna"
      ]
    },
    {
      "type": "pr_reviewed",
      "time": "2023-11-06T07:36:45.000Z",
      "title": "coronasafe/care_fe#6543",
      "link": "https://github.com/coronasafe/care_fe/pull/6543#pullrequestreview-1714424830",
      "text": "Replace useDispatch w. useQuery/request: Notifications (src/Components/Notifications/**) #6392"
    },
    {
      "type": "comment_created",
      "title": "coronasafe/care_fe#6392",
      "time": "2023-11-05T23:15:47.000Z",
      "link": "https://github.com/coronasafe/care_fe/issues/6392#issuecomment-1793878114",
      "text": "I created a pull request for the issue. What are the next steps?"
    },
    {
      "type": "pr_opened",
      "title": "coronasafe/care_fe#6543",
      "time": "2023-11-05T23:05:46.000Z",
      "link": "https://github.com/coronasafe/care_fe/pull/6543",
      "text": "Issue 6392"
    },
    {
      "type": "comment_created",
      "title": "coronasafe/care_fe#6392",
      "time": "2023-11-05T15:39:14.000Z",
      "link": "https://github.com/coronasafe/care_fe/issues/6392#issuecomment-1793771258",
      "text": "Hi @rithviknishad I edited all components in the Notifications folder (change useDispatch). This is my fork https://github.com/adriansliva/issue-6392, and should I now create a branch?\r\n\r\nI apologize for the delay in editing the code. Thanks for your answer."
    },
    {
      "type": "comment_created",
      "title": "coronasafe/care_fe#6392",
      "time": "2023-10-26T11:51:37.000Z",
      "link": "https://github.com/coronasafe/care_fe/issues/6392#issuecomment-1780961446",
      "text": "@rithviknishad I can't push the changes I created in the code\r\nI created my own branch and I'm trying to put what I made into it but it doesn't work. Can you help or advise me thank you"
    },
    {
      "type": "comment_created",
      "title": "coronasafe/care_fe#6392",
      "time": "2023-10-26T11:37:40.000Z",
      "link": "https://github.com/coronasafe/care_fe/issues/6392#issuecomment-1780942950",
      "text": "I have to have this problem because it relates to a subject at the university I am studying at and I can no longer change the role I have chosen. Until recently I didn't have time to solve it, but I have already started working on its implementation. thank you for your understanding."
    },
    {
      "type": "comment_created",
      "title": "coronasafe/care_fe#6392",
      "time": "2023-10-26T11:34:24.000Z",
      "link": "https://github.com/coronasafe/care_fe/issues/6392#issuecomment-1780938842",
      "text": "@shyamprakash123 im still working on this issue "
    },
    {
      "type": "comment_created",
      "title": "coronasafe/care_fe#6392",
      "time": "2023-10-20T08:10:21.000Z",
      "link": "https://github.com/coronasafe/care_fe/issues/6392#issuecomment-1772278796",
      "text": "specifically today I will add the first solution"
    },
    {
      "type": "comment_created",
      "title": "coronasafe/care_fe#6392",
      "time": "2023-10-20T08:08:33.000Z",
      "link": "https://github.com/coronasafe/care_fe/issues/6392#issuecomment-1772276322",
      "text": "sorry for the inactivity but I'm working on it, the solution will be ready in the next few days"
    },
    {
      "type": "comment_created",
      "title": "coronasafe/care_fe#6392",
      "time": "2023-10-04T05:41:11.000Z",
      "link": "https://github.com/coronasafe/care_fe/issues/6392#issuecomment-1746172400",
      "text": "Hi can you please assign me this issue?"
    },
    {
      "type": "pr_merged",
      "title": "coronasafe/care_fe#6543",
      "time": "2023-11-07T11:27:36Z",
      "link": "https://github.com/coronasafe/care_fe/pull/6543",
      "text": "Replace useDispatch w. useQuery/request: Notifications (src/Components/Notifications/**) #6392"
    }
  ],
  "open_prs": [],
  "authored_issue_and_pr": []
}