{
  "last_updated": "2023-11-17T09:40:19Z",
  "activity": [
    {
      "type": "pr_opened",
      "title": "coronasafe/care_fe#6661",
      "time": "2023-11-17T09:40:19Z",
      "link": "https://github.com/coronasafe/care_fe/pull/6661",
      "text": "(Fix)-Address scrolling issue in CommentSection"
    },
    {
      "type": "pr_opened",
      "title": "coronasafe/care_fe#7254",
      "time": "2024-02-23T07:30:07Z",
      "link": "https://github.com/coronasafe/care_fe/pull/7254",
      "text": "Bed Management System Redesign"
    }
  ],
  "open_prs": [],
  "authored_issue_and_pr": []
}