{
  "last_updated": "2024-11-01T06:30:43.000Z",
  "activity": [
    {
      "type": "pr_opened",
      "title": "ohcnetwork/care_fe#8976",
      "time": "2024-11-01T06:30:43.000Z",
      "link": "https://github.com/ohcnetwork/care_fe/pull/8976",
      "text": "Issues/8762/reposition loader"
    }
  ],
  "open_prs": [
    {
      "link": "https://github.com/ohcnetwork/care_fe/pull/8976",
      "title": "Issues/8762/reposition loader",
      "stale_for": 0,
      "labels": []
    }
  ],
  "authored_issue_and_pr": []
}